{
	"textures": [
		{
			"image": "ui/ui.png",
			"format": "RGBA8888",
			"size": {
				"w": 1034,
				"h": 2046
			},
			"scale": 1,
			"frames": [
				{
					"filename": "ISWFONT3.png",
					"rotated": false,
					"trimmed": true,
					"sourceSize": {
						"w": 1082,
						"h": 512
					},
					"spriteSourceSize": {
						"x": 25,
						"y": 9,
						"w": 1032,
						"h": 490
					},
					"frame": {
						"x": 1,
						"y": 1,
						"w": 1032,
						"h": 490
					}
				},
				{
					"filename": "hexBackground2.png",
					"rotated": false,
					"trimmed": false,
					"sourceSize": {
						"w": 1024,
						"h": 1024
					},
					"spriteSourceSize": {
						"x": 0,
						"y": 0,
						"w": 1024,
						"h": 1024
					},
					"frame": {
						"x": 1,
						"y": 493,
						"w": 1024,
						"h": 1024
					}
				},
				{
					"filename": "shipPanel.png",
					"rotated": false,
					"trimmed": false,
					"sourceSize": {
						"w": 427,
						"h": 526
					},
					"spriteSourceSize": {
						"x": 0,
						"y": 0,
						"w": 427,
						"h": 526
					},
					"frame": {
						"x": 1,
						"y": 1519,
						"w": 427,
						"h": 526
					}
				},
				{
					"filename": "buttonNormal.png",
					"rotated": false,
					"trimmed": true,
					"sourceSize": {
						"w": 260,
						"h": 38
					},
					"spriteSourceSize": {
						"x": 0,
						"y": 1,
						"w": 260,
						"h": 37
					},
					"frame": {
						"x": 430,
						"y": 1519,
						"w": 260,
						"h": 37
					}
				},
				{
					"filename": "buttonNormal2.png",
					"rotated": false,
					"trimmed": true,
					"sourceSize": {
						"w": 260,
						"h": 38
					},
					"spriteSourceSize": {
						"x": 0,
						"y": 1,
						"w": 260,
						"h": 37
					},
					"frame": {
						"x": 692,
						"y": 1519,
						"w": 260,
						"h": 37
					}
				},
				{
					"filename": "gui_beam_64.png",
					"rotated": false,
					"trimmed": false,
					"sourceSize": {
						"w": 64,
						"h": 64
					},
					"spriteSourceSize": {
						"x": 0,
						"y": 0,
						"w": 64,
						"h": 64
					},
					"frame": {
						"x": 954,
						"y": 1519,
						"w": 64,
						"h": 64
					}
				},
				{
					"filename": "buttonOver.png",
					"rotated": false,
					"trimmed": true,
					"sourceSize": {
						"w": 260,
						"h": 38
					},
					"spriteSourceSize": {
						"x": 0,
						"y": 1,
						"w": 260,
						"h": 37
					},
					"frame": {
						"x": 430,
						"y": 1558,
						"w": 260,
						"h": 37
					}
				},
				{
					"filename": "buttonOver2.png",
					"rotated": false,
					"trimmed": true,
					"sourceSize": {
						"w": 260,
						"h": 38
					},
					"spriteSourceSize": {
						"x": 0,
						"y": 1,
						"w": 260,
						"h": 37
					},
					"frame": {
						"x": 692,
						"y": 1558,
						"w": 260,
						"h": 37
					}
				},
				{
					"filename": "gui_lrotate_64.png",
					"rotated": false,
					"trimmed": false,
					"sourceSize": {
						"w": 64,
						"h": 64
					},
					"spriteSourceSize": {
						"x": 0,
						"y": 0,
						"w": 64,
						"h": 64
					},
					"frame": {
						"x": 954,
						"y": 1585,
						"w": 64,
						"h": 64
					}
				},
				{
					"filename": "tab.png",
					"rotated": false,
					"trimmed": false,
					"sourceSize": {
						"w": 256,
						"h": 64
					},
					"spriteSourceSize": {
						"x": 0,
						"y": 0,
						"w": 256,
						"h": 64
					},
					"frame": {
						"x": 430,
						"y": 1597,
						"w": 256,
						"h": 64
					}
				},
				{
					"filename": "button4_hover.png",
					"rotated": false,
					"trimmed": true,
					"sourceSize": {
						"w": 128,
						"h": 59
					},
					"spriteSourceSize": {
						"x": 1,
						"y": 4,
						"w": 127,
						"h": 50
					},
					"frame": {
						"x": 688,
						"y": 1597,
						"w": 127,
						"h": 50
					}
				},
				{
					"filename": "button3_hover.png",
					"rotated": false,
					"trimmed": false,
					"sourceSize": {
						"w": 107,
						"h": 39
					},
					"spriteSourceSize": {
						"x": 0,
						"y": 0,
						"w": 107,
						"h": 39
					},
					"frame": {
						"x": 817,
						"y": 1597,
						"w": 107,
						"h": 39
					}
				},
				{
					"filename": "button3_off.png",
					"rotated": false,
					"trimmed": false,
					"sourceSize": {
						"w": 107,
						"h": 39
					},
					"spriteSourceSize": {
						"x": 0,
						"y": 0,
						"w": 107,
						"h": 39
					},
					"frame": {
						"x": 817,
						"y": 1638,
						"w": 107,
						"h": 39
					}
				},
				{
					"filename": "button3_on.png",
					"rotated": false,
					"trimmed": false,
					"sourceSize": {
						"w": 107,
						"h": 39
					},
					"spriteSourceSize": {
						"x": 0,
						"y": 0,
						"w": 107,
						"h": 39
					},
					"frame": {
						"x": 926,
						"y": 1651,
						"w": 107,
						"h": 39
					}
				},
				{
					"filename": "button1_hover.png",
					"rotated": false,
					"trimmed": false,
					"sourceSize": {
						"w": 107,
						"h": 32
					},
					"spriteSourceSize": {
						"x": 0,
						"y": 0,
						"w": 107,
						"h": 32
					},
					"frame": {
						"x": 688,
						"y": 1649,
						"w": 107,
						"h": 32
					}
				},
				{
					"filename": "button1_off.png",
					"rotated": false,
					"trimmed": false,
					"sourceSize": {
						"w": 107,
						"h": 32
					},
					"spriteSourceSize": {
						"x": 0,
						"y": 0,
						"w": 107,
						"h": 32
					},
					"frame": {
						"x": 797,
						"y": 1679,
						"w": 107,
						"h": 32
					}
				},
				{
					"filename": "button1_on.png",
					"rotated": false,
					"trimmed": false,
					"sourceSize": {
						"w": 107,
						"h": 32
					},
					"spriteSourceSize": {
						"x": 0,
						"y": 0,
						"w": 107,
						"h": 32
					},
					"frame": {
						"x": 906,
						"y": 1692,
						"w": 107,
						"h": 32
					}
				},
				{
					"filename": "button2_hover.png",
					"rotated": false,
					"trimmed": false,
					"sourceSize": {
						"w": 96,
						"h": 33
					},
					"spriteSourceSize": {
						"x": 0,
						"y": 0,
						"w": 96,
						"h": 33
					},
					"frame": {
						"x": 430,
						"y": 1663,
						"w": 96,
						"h": 33
					}
				},
				{
					"filename": "button2_off.png",
					"rotated": false,
					"trimmed": false,
					"sourceSize": {
						"w": 96,
						"h": 33
					},
					"spriteSourceSize": {
						"x": 0,
						"y": 0,
						"w": 96,
						"h": 33
					},
					"frame": {
						"x": 528,
						"y": 1663,
						"w": 96,
						"h": 33
					}
				},
				{
					"filename": "flag12.jpg",
					"rotated": false,
					"trimmed": false,
					"sourceSize": {
						"w": 60,
						"h": 49
					},
					"spriteSourceSize": {
						"x": 0,
						"y": 0,
						"w": 60,
						"h": 49
					},
					"frame": {
						"x": 626,
						"y": 1663,
						"w": 60,
						"h": 49
					}
				},
				{
					"filename": "button2_on.png",
					"rotated": false,
					"trimmed": false,
					"sourceSize": {
						"w": 96,
						"h": 33
					},
					"spriteSourceSize": {
						"x": 0,
						"y": 0,
						"w": 96,
						"h": 33
					},
					"frame": {
						"x": 688,
						"y": 1683,
						"w": 96,
						"h": 33
					}
				},
				{
					"filename": "gui_missiles_64.png",
					"rotated": false,
					"trimmed": false,
					"sourceSize": {
						"w": 64,
						"h": 64
					},
					"spriteSourceSize": {
						"x": 0,
						"y": 0,
						"w": 64,
						"h": 64
					},
					"frame": {
						"x": 786,
						"y": 1713,
						"w": 64,
						"h": 64
					}
				},
				{
					"filename": "flag16.jpg",
					"rotated": false,
					"trimmed": false,
					"sourceSize": {
						"w": 52,
						"h": 52
					},
					"spriteSourceSize": {
						"x": 0,
						"y": 0,
						"w": 52,
						"h": 52
					},
					"frame": {
						"x": 852,
						"y": 1713,
						"w": 52,
						"h": 52
					}
				},
				{
					"filename": "gui_move_64.png",
					"rotated": false,
					"trimmed": false,
					"sourceSize": {
						"w": 64,
						"h": 64
					},
					"spriteSourceSize": {
						"x": 0,
						"y": 0,
						"w": 64,
						"h": 64
					},
					"frame": {
						"x": 906,
						"y": 1726,
						"w": 64,
						"h": 64
					}
				},
				{
					"filename": "flag17.jpg",
					"rotated": false,
					"trimmed": false,
					"sourceSize": {
						"w": 52,
						"h": 52
					},
					"spriteSourceSize": {
						"x": 0,
						"y": 0,
						"w": 52,
						"h": 52
					},
					"frame": {
						"x": 852,
						"y": 1767,
						"w": 52,
						"h": 52
					}
				},
				{
					"filename": "flag8.jpg",
					"rotated": false,
					"trimmed": false,
					"sourceSize": {
						"w": 61,
						"h": 50
					},
					"spriteSourceSize": {
						"x": 0,
						"y": 0,
						"w": 61,
						"h": 50
					},
					"frame": {
						"x": 972,
						"y": 1726,
						"w": 61,
						"h": 50
					}
				},
				{
					"filename": "flag7.jpg",
					"rotated": false,
					"trimmed": false,
					"sourceSize": {
						"w": 60,
						"h": 41
					},
					"spriteSourceSize": {
						"x": 0,
						"y": 0,
						"w": 60,
						"h": 41
					},
					"frame": {
						"x": 972,
						"y": 1778,
						"w": 60,
						"h": 41
					}
				},
				{
					"filename": "gui_rrotate_64.png",
					"rotated": false,
					"trimmed": false,
					"sourceSize": {
						"w": 64,
						"h": 64
					},
					"spriteSourceSize": {
						"x": 0,
						"y": 0,
						"w": 64,
						"h": 64
					},
					"frame": {
						"x": 906,
						"y": 1792,
						"w": 64,
						"h": 64
					}
				},
				{
					"filename": "flag1.jpg",
					"rotated": false,
					"trimmed": false,
					"sourceSize": {
						"w": 60,
						"h": 40
					},
					"spriteSourceSize": {
						"x": 0,
						"y": 0,
						"w": 60,
						"h": 40
					},
					"frame": {
						"x": 972,
						"y": 1821,
						"w": 60,
						"h": 40
					}
				},
				{
					"filename": "gui_target_64.png",
					"rotated": false,
					"trimmed": false,
					"sourceSize": {
						"w": 64,
						"h": 64
					},
					"spriteSourceSize": {
						"x": 0,
						"y": 0,
						"w": 64,
						"h": 64
					},
					"frame": {
						"x": 430,
						"y": 1863,
						"w": 64,
						"h": 64
					}
				},
				{
					"filename": "flag10.jpg",
					"rotated": false,
					"trimmed": false,
					"sourceSize": {
						"w": 60,
						"h": 40
					},
					"spriteSourceSize": {
						"x": 0,
						"y": 0,
						"w": 60,
						"h": 40
					},
					"frame": {
						"x": 430,
						"y": 1821,
						"w": 60,
						"h": 40
					}
				},
				{
					"filename": "flag13.jpg",
					"rotated": false,
					"trimmed": false,
					"sourceSize": {
						"w": 60,
						"h": 40
					},
					"spriteSourceSize": {
						"x": 0,
						"y": 0,
						"w": 60,
						"h": 40
					},
					"frame": {
						"x": 492,
						"y": 1821,
						"w": 60,
						"h": 40
					}
				},
				{
					"filename": "flag2.jpg",
					"rotated": false,
					"trimmed": false,
					"sourceSize": {
						"w": 60,
						"h": 40
					},
					"spriteSourceSize": {
						"x": 0,
						"y": 0,
						"w": 60,
						"h": 40
					},
					"frame": {
						"x": 430,
						"y": 1779,
						"w": 60,
						"h": 40
					}
				},
				{
					"filename": "flag6.jpg",
					"rotated": false,
					"trimmed": false,
					"sourceSize": {
						"w": 60,
						"h": 39
					},
					"spriteSourceSize": {
						"x": 0,
						"y": 0,
						"w": 60,
						"h": 39
					},
					"frame": {
						"x": 492,
						"y": 1779,
						"w": 60,
						"h": 39
					}
				},
				{
					"filename": "flag18.jpg",
					"rotated": false,
					"trimmed": false,
					"sourceSize": {
						"w": 52,
						"h": 52
					},
					"spriteSourceSize": {
						"x": 0,
						"y": 0,
						"w": 52,
						"h": 52
					},
					"frame": {
						"x": 430,
						"y": 1718,
						"w": 52,
						"h": 52
					}
				},
				{
					"filename": "flag4.jpg",
					"rotated": false,
					"trimmed": false,
					"sourceSize": {
						"w": 58,
						"h": 50
					},
					"spriteSourceSize": {
						"x": 0,
						"y": 0,
						"w": 58,
						"h": 50
					},
					"frame": {
						"x": 484,
						"y": 1718,
						"w": 58,
						"h": 50
					}
				},
				{
					"filename": "flag3.jpg",
					"rotated": false,
					"trimmed": false,
					"sourceSize": {
						"w": 56,
						"h": 50
					},
					"spriteSourceSize": {
						"x": 0,
						"y": 0,
						"w": 56,
						"h": 50
					},
					"frame": {
						"x": 544,
						"y": 1718,
						"w": 56,
						"h": 50
					}
				},
				{
					"filename": "flag9.jpg",
					"rotated": false,
					"trimmed": false,
					"sourceSize": {
						"w": 60,
						"h": 30
					},
					"spriteSourceSize": {
						"x": 0,
						"y": 0,
						"w": 60,
						"h": 30
					},
					"frame": {
						"x": 602,
						"y": 1714,
						"w": 60,
						"h": 30
					}
				},
				{
					"filename": "flag15.jpg",
					"rotated": false,
					"trimmed": false,
					"sourceSize": {
						"w": 59,
						"h": 48
					},
					"spriteSourceSize": {
						"x": 0,
						"y": 0,
						"w": 59,
						"h": 48
					},
					"frame": {
						"x": 664,
						"y": 1718,
						"w": 59,
						"h": 48
					}
				},
				{
					"filename": "flag14.jpg",
					"rotated": false,
					"trimmed": false,
					"sourceSize": {
						"w": 58,
						"h": 48
					},
					"spriteSourceSize": {
						"x": 0,
						"y": 0,
						"w": 58,
						"h": 48
					},
					"frame": {
						"x": 725,
						"y": 1718,
						"w": 58,
						"h": 48
					}
				},
				{
					"filename": "flag11.jpg",
					"rotated": false,
					"trimmed": false,
					"sourceSize": {
						"w": 51,
						"h": 50
					},
					"spriteSourceSize": {
						"x": 0,
						"y": 0,
						"w": 51,
						"h": 50
					},
					"frame": {
						"x": 602,
						"y": 1746,
						"w": 51,
						"h": 50
					}
				},
				{
					"filename": "flag5.jpg",
					"rotated": false,
					"trimmed": false,
					"sourceSize": {
						"w": 50,
						"h": 50
					},
					"spriteSourceSize": {
						"x": 0,
						"y": 0,
						"w": 50,
						"h": 50
					},
					"frame": {
						"x": 430,
						"y": 1929,
						"w": 50,
						"h": 50
					}
				}
			]
		}
	],
	"meta": {
		"app": "https://www.codeandweb.com/texturepacker",
		"version": "3.0",
		"smartupdate": "$TexturePacker:SmartUpdate:c9d7de87048f6dca34e9081fad0676d2:8236725a05527f1223ad4180efd2c164:5b04aa198265472a3c5f56958d78e97b$"
	}
}
